premium_futures_mcp/__init__.py
premium_futures_mcp/__main__.py
premium_futures_mcp/cache.py
premium_futures_mcp/client.py
premium_futures_mcp/config.py
premium_futures_mcp/fallback_data.py
premium_futures_mcp/handlers.py
premium_futures_mcp/intelligent_tools.py
premium_futures_mcp/public_client.py
premium_futures_mcp/remote_auth.py
premium_futures_mcp/response_optimizer.py
premium_futures_mcp/server.py
premium_futures_mcp/tools.py
premium_futures_mcp-1.6.0.dist-info/licenses/LICENSE
premium_futures_mcp-1.6.0.dist-info/METADATA
premium_futures_mcp-1.6.0.dist-info/WHEEL
premium_futures_mcp-1.6.0.dist-info/entry_points.txt
premium_futures_mcp-1.6.0.dist-info/top_level.txt
premium_futures_mcp-1.6.0.dist-info/RECORD
