Metadata-Version: 2.4
Name: premium-futures-mcp
Version: 1.6.0
Summary: Premium Binance Futures MCP Server - Advanced trading tools for professional traders
Home-page: https://github.com/alexcandrabersiva/premium_futures_mcp
Author: Smart AI Trading
Author-email: Premium Trading Solutions <support@smartaitrading.org>
License: Proprietary
Project-URL: Homepage, https://github.com/alexcandrabersiva/premium_futures_mcp
Project-URL: Documentation, https://github.com/alexcandrabersiva/premium_futures_mcp#readme
Project-URL: Repository, https://github.com/alexcandrabersiva/premium_futures_mcp
Project-URL: Issues, https://github.com/alexcandrabersiva/premium_futures_mcp/issues
Classifier: Development Status :: 4 - Beta
Classifier: Intended Audience :: Financial and Insurance Industry
Classifier: Operating System :: OS Independent
Classifier: Programming Language :: Python :: 3
Classifier: Programming Language :: Python :: 3.10
Classifier: Programming Language :: Python :: 3.11
Classifier: Programming Language :: Python :: 3.12
Classifier: Topic :: Office/Business :: Financial :: Investment
Requires-Python: >=3.10
License-File: LICENSE
Requires-Dist: mcp>=1.0.0
Requires-Dist: httpx>=0.25.0
Requires-Dist: aiohttp>=3.8.0
Requires-Dist: pydantic>=2.0.0
Requires-Dist: python-dotenv>=1.0.0
Requires-Dist: redis>=5.0.0
Provides-Extra: dev
Requires-Dist: pytest>=7.0.0; extra == "dev"
Requires-Dist: pytest-asyncio>=0.21.0; extra == "dev"
Requires-Dist: black>=23.0.0; extra == "dev"
Requires-Dist: isort>=5.0.0; extra == "dev"
Requires-Dist: mypy>=1.0.0; extra == "dev"
Dynamic: author
Dynamic: home-page
Dynamic: license-file
Dynamic: requires-python
